MANIFEST.in
README.txt
setup.cfg
setup.py
openbiblio/__init__.py
openbiblio/utils.py
openbiblio/websetup.py
openbiblio.egg-info/PKG-INFO
openbiblio.egg-info/SOURCES.txt
openbiblio.egg-info/dependency_links.txt
openbiblio.egg-info/entry_points.txt
openbiblio.egg-info/not-zip-safe
openbiblio.egg-info/paster_plugins.txt
openbiblio.egg-info/requires.txt
openbiblio.egg-info/top_level.txt
openbiblio/commands/__init__.py
openbiblio/commands/dedup.py
openbiblio/commands/fetch.py
openbiblio/commands/gut_loader.py
openbiblio/commands/marc_editor.py
openbiblio/commands/marc_loader.py
openbiblio/commands/materialise.py
openbiblio/config/__init__.py
openbiblio/config/deployment.ini_tmpl
openbiblio/config/environment.py
openbiblio/config/middleware.py
openbiblio/config/routing.py
openbiblio/controllers/__init__.py
openbiblio/controllers/account.py
openbiblio/controllers/changeset.py
openbiblio/controllers/collection.py
openbiblio/controllers/error.py
openbiblio/controllers/graph.py
openbiblio/controllers/home.py
openbiblio/controllers/isbn.py
openbiblio/controllers/modelview.py
openbiblio/controllers/proxy.py
openbiblio/controllers/remote.py
openbiblio/controllers/search.py
openbiblio/controllers/sparql.py
openbiblio/controllers/uuidalloc.py
openbiblio/lib/__init__.py
openbiblio/lib/app_globals.py
openbiblio/lib/authenticator.py
openbiblio/lib/base.py
openbiblio/lib/bibtex.py
openbiblio/lib/helpers.py
openbiblio/lib/marc.py
openbiblio/lib/name.py
openbiblio/lib/namespace.py
openbiblio/lib/utils.py
openbiblio/lib/vocab.py
openbiblio/lib/xapindex.py
openbiblio/model/__init__.py
openbiblio/model/account.py
openbiblio/model/base.py
openbiblio/model/collection.py
openbiblio/model/entity.py
openbiblio/model/entry.py
openbiblio/model/misc.py
openbiblio/model/subject.py
openbiblio/public/idealab.png
openbiblio/public/robots.txt
openbiblio/public/terms.html
openbiblio/public/css/book.css
openbiblio/public/css/extra.css
openbiblio/public/css/jquery-ui-1.8.9.custom.css
openbiblio/public/css/search.css
openbiblio/public/css/style.css
openbiblio/public/demos/sparql.html
openbiblio/public/demos/wp-bibliographica.js
openbiblio/public/js/entry.js
openbiblio/public/js/jquery-ui-1.8.9.custom.min.js
openbiblio/public/js/vendor/sparql.js
openbiblio/templates/__init__.py
