Metadata-Version: 1.0
Name: openbiblio
Version: 0.4.1
Summary: RDF Open Source Bibliographic Catalogue System
Home-page: http://bibliographica.org/
Author: Open Knowledge Foundation
Author-email: info@okfn.org
License: AGPL
Platform: UNKNOWN
